balance_point_clustering/__init__.py
balance_point_clustering/clustering.py
balance_point_clustering/tests.py
balance_point_clustering-0.2.0.dist-info/LICENSE.txt
balance_point_clustering-0.2.0.dist-info/METADATA
balance_point_clustering-0.2.0.dist-info/WHEEL
balance_point_clustering-0.2.0.dist-info/top_level.txt
balance_point_clustering-0.2.0.dist-info/RECORD
