Metadata-Version: 2.1
Name: balance-point-clustering
Version: 0.2.0
Summary: A Python package for Balance Point Clustering with dynamic cluster determination.
Home-page: https://github.com/Impssn/Balance-Point-Clustering.git
Author: Sathya Narayanan
Author-email: impssn@gmail.com
Classifier: Programming Language :: Python :: 3
Classifier: License :: OSI Approved :: MIT License
Classifier: Operating System :: OS Independent
License-File: LICENSE.txt
Requires-Dist: numpy
Requires-Dist: pandas
